sources/new/control_iris.sv
module control_iris #(
    parameter TIME_STEPS     = 64,
    parameter PIPELINE_DEPTH = 8
)(
    input  clk,
    input  reset_n,
    output reg sample_reset,
    output reg reset_ly1,
    output reg reset_ly2,
    output reg reset_ly3,
    output reg reset_ly4,
    output reg count_enable,
    output reg result_valid
);

    localparam LY1_RST_DELAY = 0;
    localparam LY2_RST_DELAY = 2;
    localparam LY3_RST_DELAY = 4;
    localparam LY4_RST_DELAY = 6;
    
    reg [15:0] cycle_count;
    wire       processing_done = (cycle_count == TIME_STEPS + PIPELINE_DEPTH);

    always @(posedge clk or negedge reset_n) begin
        if (!reset_n) begin
            cycle_count  <= 0;
            sample_reset <= 1'b1;
            reset_ly1    <= 1'b1;
            reset_ly2    <= 1'b1;
            reset_ly3    <= 1'b1;
            reset_ly4    <= 1'b1;
            count_enable <= 1'b0;
            result_valid <= 1'b0;
        end else begin
            sample_reset <= 1'b0;
            reset_ly1    <= 1'b0;
            reset_ly2    <= 1'b0;
            reset_ly3    <= 1'b0;
            reset_ly4    <= 1'b0;
            result_valid <= 1'b0;
            
            if (processing_done) begin
                cycle_count  <= 0;
                result_valid <= 1'b1;
            end else begin
                cycle_count <= cycle_count + 1;
            end
            
            if (cycle_count == LY1_RST_DELAY) reset_ly1 <= 1'b1;
            if (cycle_count == LY2_RST_DELAY) reset_ly2 <= 1'b1;
            if (cycle_count == LY3_RST_DELAY) reset_ly3 <= 1'b1;
            if (cycle_count == LY4_RST_DELAY) reset_ly4 <= 1'b1;
            if (cycle_count == 0)            sample_reset <= 1'b1;
            
            count_enable <= (cycle_count >= PIPELINE_DEPTH) && 
                            (cycle_count < PIPELINE_DEPTH + TIME_STEPS);
        end
    end

endmodule

snn_iris_project/snn_iris_project.srcs/sim_1/new/tb_control_iris.sv
`timescale 1ns/1ps

module tb_control_iris;
    reg  clk;
    reg  reset_n;
    wire sample_reset;
    wire reset_ly1;
    wire reset_ly2;
    wire reset_ly3;
    wire reset_ly4;
    wire count_enable;
    wire result_valid;
    
    control_iris #(
        .TIME_STEPS    (8),  // Reduced for simulation
        .PIPELINE_DEPTH(2)   // Reduced for simulation
    ) uut (
        .clk         (clk),
        .reset_n     (reset_n),
        .sample_reset(sample_reset),
        .reset_ly1   (reset_ly1),
        .reset_ly2   (reset_ly2),
        .reset_ly3   (reset_ly3),
        .reset_ly4   (reset_ly4),
        .count_enable(count_enable),
        .result_valid(result_valid)
    );

    always #5 clk = ~clk;
    
    initial begin
        clk     = 0;
        reset_n = 0;
        #20 reset_n = 1;
        
        // Wait for 2 complete processing cycles
        repeat(2) @(posedge result_valid);
        #50 $finish;
    end
    
    always @(posedge result_valid) begin
        $display($time, " Result valid pulse detected");
    end
    
    initial begin
        $dumpfile("waveform.vcd");
        $dumpvars(0, tb_control_iris);
    end

endmodule

snn_iris_project/snn_iris_project.sim/sim_1/behav/xsim/waveform.vcd
$date
   Sun Jul  6 14:13:17 2025
$end

$version
  2023.2
  $dumpfile ("waveform.vcd") 
$end

$timescale
  1ps
$end

$scope module tb_control_iris $end
$var reg 1 ! clk $end
$var reg 1 " reset_n $end
$var wire 1 # sample_reset $end
$var wire 1 $ reset_ly1 $end
$var wire 1 % reset_ly2 $end
$var wire 1 & reset_ly3 $end
$var wire 1 ' reset_ly4 $end
$var wire 1 ( count_enable $end
$var wire 1 ) result_valid $end
$scope module uut $end
$var wire 1 * clk $end
$var wire 1 + reset_n $end
$var reg 1 , sample_reset $end
$var reg 1 - reset_ly1 $end
$var reg 1 . reset_ly2 $end
$var reg 1 / reset_ly3 $end
$var reg 1 0 reset_ly4 $end
$var reg 1 1 count_enable $end
$var reg 1 2 result_valid $end
$var reg 16 3 cycle_count [15:0] $end
$var wire 1 4 processing_done $end
$upscope $end
$upscope $end
$enddefinitions $end

#0
$dumpvars
0!
0"
1#
1$
1%
1&
1'
0(
0)
0*
0+
1,
1-
1.
1/
10
01
02
b0 3
04
$end

#5000
1!
1*

#10000
0!
0*

#15000
1!
1*

#20000
0!
1"
0*
1+

#25000
1!
0%
0&
0'
1*
1,
1-
0.
0/
00
b1 3

#30000
0!
0*

#35000
1!
0#
0$
1*
0,
0-
b10 3

#40000
0!
0*

#45000
1!
1%
1(
1*
1.
11
b11 3

#50000
0!
0*

#55000
1!
0%
1*
0.
b100 3

#60000
0!
0*

#65000
1!
1&
1*
1/
b101 3

#70000
0!
0*

#75000
1!
0&
1*
0/
b110 3

#80000
0!
0*

#85000
1!
1'
1*
10
b111 3

#90000
0!
0*

#95000
1!
0'
1*
00
b1000 3

#100000
0!
0*

#105000
1!
1*
b1001 3

#110000
0!
0*

#115000
1!
1*
b1010 3
14

#120000
0!
0*

#125000
1!
0(
1)
1*
01
12
b0 3
04

#130000
0!
0*

#135000
1!
1#
1$
0)
1*
1,
1-
02
b1 3

#140000
0!
0*

#145000
1!
0#
0$
1*
0,
0-
b10 3

#150000
0!
0*

#155000
1!
1%
1(
1*
1.
11
b11 3

#160000
0!
0*

#165000
1!
0%
1*
0.
b100 3

#170000
0!
0*

#175000
1!
1&
1*
1/
b101 3

#180000
0!
0*

#185000
1!
0&
1*
0/
b110 3

#190000
0!
0*

#195000
1!
1'
1*
10
b111 3

#200000
0!
0*

#205000
1!
0'
1*
00
b1000 3

#210000
0!
0*

#215000
1!
1*
b1001 3

#220000
0!
0*

#225000
1!
1*
b1010 3
14

#230000
0!
0*

#235000
1!
0(
1)
1*
01
12
b0 3
04

#240000
0!
0*

#245000
1!
1#
1$
0)
1*
1,
1-
02
b1 3

#250000
0!
0*

#255000
1!
0#
0$
1*
0,
0-
b10 3

#260000
0!
0*

#265000
1!
1%
1(
1*
1.
11
b11 3

#270000
0!
0*

#275000
1!
0%
1*
0.
b100 3

